fit_file_faker/__init__.py
fit_file_faker/app.py
fit_file_faker/app_registry.py
fit_file_faker/config.py
fit_file_faker/fit_editor.py
fit_file_faker/utils.py
fit_file_faker/vendor/fit_tool/__init__.py
fit_file_faker/vendor/fit_tool/base_type.py
fit_file_faker/vendor/fit_tool/data_message.py
fit_file_faker/vendor/fit_tool/definition_message.py
fit_file_faker/vendor/fit_tool/developer_field.py
fit_file_faker/vendor/fit_tool/developer_field_definition.py
fit_file_faker/vendor/fit_tool/endian.py
fit_file_faker/vendor/fit_tool/field.py
fit_file_faker/vendor/fit_tool/field_component.py
fit_file_faker/vendor/fit_tool/field_definition.py
fit_file_faker/vendor/fit_tool/fit_file.py
fit_file_faker/vendor/fit_tool/fit_file_builder.py
fit_file_faker/vendor/fit_tool/fit_file_header.py
fit_file_faker/vendor/fit_tool/generic_message.py
fit_file_faker/vendor/fit_tool/message.py
fit_file_faker/vendor/fit_tool/record.py
fit_file_faker/vendor/fit_tool/sub_field.py
fit_file_faker/vendor/fit_tool/examples/modify_activity_example.py
fit_file_faker/vendor/fit_tool/examples/read_activity_example.py
fit_file_faker/vendor/fit_tool/examples/write_activity_example.py
fit_file_faker/vendor/fit_tool/examples/write_course_example.py
fit_file_faker/vendor/fit_tool/examples/write_workout_example.py
fit_file_faker/vendor/fit_tool/gen/__init__.py
fit_file_faker/vendor/fit_tool/gen/gen_profile.py
fit_file_faker/vendor/fit_tool/gen/profile.py
fit_file_faker/vendor/fit_tool/profile/profile_type.py
fit_file_faker/vendor/fit_tool/profile/messages/accelerometer_data_message.py
fit_file_faker/vendor/fit_tool/profile/messages/activity_message.py
fit_file_faker/vendor/fit_tool/profile/messages/ant_channel_id_message.py
fit_file_faker/vendor/fit_tool/profile/messages/ant_rx_message.py
fit_file_faker/vendor/fit_tool/profile/messages/ant_tx_message.py
fit_file_faker/vendor/fit_tool/profile/messages/aviation_attitude_message.py
fit_file_faker/vendor/fit_tool/profile/messages/barometer_data_message.py
fit_file_faker-2.1.2.dist-info/licenses/LICENSE.md
fit_file_faker-2.1.2.dist-info/METADATA
fit_file_faker-2.1.2.dist-info/WHEEL
fit_file_faker-2.1.2.dist-info/entry_points.txt
fit_file_faker-2.1.2.dist-info/top_level.txt
fit_file_faker-2.1.2.dist-info/RECORD
