Metadata-Version: 2.4
Name: fit-file-faker
Version: 2.1.2
Summary: Modify and auto-upload FIT files from third-party platforms to unlock Garmin Connect features
Author-email: Josh Taillon <jat255@gmail.com>
Project-URL: Homepage, https://github.com/jat255/Fit-File-Faker
Project-URL: Issues, https://github.com/jat255/Fit-File-Faker/issues
Classifier: Programming Language :: Python :: 3
Classifier: License :: OSI Approved :: MIT License
Classifier: Operating System :: OS Independent
Requires-Python: >=3.12.0
License-File: LICENSE.md
Requires-Dist: garth>=0.5.21
Requires-Dist: platformdirs>=4.5.1
Requires-Dist: questionary>=2.1.1
Requires-Dist: rich>=14.2.0
Requires-Dist: semver>=3.0.4
Requires-Dist: watchdog>=6.0.0
Requires-Dist: bitstruct==8.11.1
Requires-Dist: openpyxl==2.5.12
Dynamic: license-file
